PyBASC/SimRunFile.py
PyBASC/SimRunFileAnibal.py
PyBASC/__init__.py
PyBASC/__main__.py
PyBASC/basc.py
PyBASC/basc_workflow_runner.py
PyBASC/pipeline.py
PyBASC/utils.py
PyBASC/data/sub_0corr_0.05_noise_2_TRs_100.nii.gz
PyBASC/data/sub_0corr_0.1_noise_2.5_TRs_100.nii.gz
PyBASC/data/sub_1corr_0.05_noise_2_TRs_100.nii.gz
PyBASC/data/sub_1corr_0.1_noise_2.5_TRs_100.nii.gz
PyBASC/data/sub_2corr_0.05_noise_2_TRs_100.nii.gz
PyBASC/data/sub_2corr_0.1_noise_2.5_TRs_100.nii.gz
PyBASC/data/sub_3corr_0.05_noise_2_TRs_100.nii.gz
PyBASC/data/sub_3corr_0.1_noise_2.5_TRs_100.nii.gz
PyBASC/data/sub_4corr_0.1_noise_2.5_TRs_100.nii.gz
PyBASC/data/sub_5corr_0.1_noise_2.5_TRs_100.nii.gz
PyBASC/data/sub_6corr_0.1_noise_2.5_TRs_100.nii.gz
PyBASC/data/sub_7corr_0.1_noise_2.5_TRs_100.nii.gz
PyBASC/data/sub_8corr_0.1_noise_2.5_TRs_100.nii.gz
PyBASC/data/sub_9corr_0.1_noise_2.5_TRs_100.nii.gz
PyBASC/masks/.DS_Store
PyBASC/masks/BG_2mm.nii.gz
PyBASC/masks/BG_3mm_TrueClust.nii.gz
PyBASC/masks/BG_HarvardOxford3mm.nii.gz
PyBASC/masks/BG_SimTrueMat_HarvardOxford3mm.nii.gz
PyBASC/masks/Bilateral_Thalamus3mm.nii.gz
PyBASC/masks/Full_BG_Sim_3mm.nii.gz
PyBASC/masks/MNI152_T1_3mm_brain_mask.nii.gz
PyBASC/masks/MNI_152_4mm.nii.gz
PyBASC/masks/MNI_152_4mm_brain.nii.gz
PyBASC/masks/SimulationMask.nii.gz
PyBASC/masks/SimulationMask1.nii.gz
PyBASC/masks/Smallmem_BGClust.nii.gz
PyBASC/masks/Striatum_HarvardOxford.nii.gz
PyBASC/masks/Striatum_HarvardOxford3mm.nii.gz
PyBASC/masks/Thalamus_HarvardOxford.nii.gz
PyBASC/masks/Thalamus_HarvardOxford3mm.nii.gz
PyBASC/masks/TrueBGClust.nii.gz
PyBASC/masks/basc7_resized_4mm.nii.gz
PyBASC/masks/cerebellum_3mm.nii.gz
PyBASC/masks/Yeo7_3mmMasks/.DS_Store
PyBASC/masks/Yeo7_3mmMasks/BilateralStriatumThalamus_3mm.nii.gz
PyBASC/masks/Yeo7_3mmMasks/FPNStriatumThalamus_3mm.nii.gz
PyBASC/masks/Yeo7_3mmMasks/MotorStriatumThalamus_3mm.nii.gz
PyBASC/masks/Yeo7_3mmMasks/YeoTest.nii.gz
PyBASC/masks/Yeo7_3mmMasks/YeoTest2.nii.gz
PyBASC-0.6.1.dist-info/.DS_Store
PyBASC-0.6.1.dist-info/METADATA
PyBASC-0.6.1.dist-info/RECORD
PyBASC-0.6.1.dist-info/WHEEL
PyBASC-0.6.1.dist-info/entry_points.txt
PyBASC-0.6.1.dist-info/top_level.txt
